{
  "layout_maps": {
    "type": "container",
    "content": [
      {
        "type": "tabbed",
        "tabs": [
          {
            "title": "Main Ward",
            "content": {
              "type": "layout",
              "orientation": "horizontal",
              "style": "wrap",
              "key": "main"
            }
          },
          {
            "title": "SVT Ward",
            "content": {
              "type": "layout",
              "orientation": "horizontal",
              "style": "wrap",
              "key": "svt"
            }
          },
          {
            "title": "Train",
            "content": {
              "type": "layout",
              "orientation": "horizontal",
              "style": "wrap",
              "key": "train"
            }
          },
          {
            "title": "Physiotherapy Ward",
            "content": {
              "type": "layout",
              "orientation": "horizontal",
              "style": "wrap",
              "key": "physiotherapy"
            }
          },
          {
            "title": "Records Room / Abandoned Ward",
            "content": {
              "type": "layout",
              "orientation": "horizontal",
              "style": "wrap",
              "key": "records"
            }
          }
        ]
      }
    ]
  }
}